portfolioperformance/__init__.py
portfolioperformance/src/__init__.py
portfolioperformance/src/app.py
portfolioperformance/src/model.py
portfolioperformance/src/modelGamma.py
portfolioperformance/src/modelNoGamma.py
portfolioperformance/src/models/JagannathanMa.py
portfolioperformance/src/models/__init__.py
portfolioperformance/src/models/bayesStein.py
portfolioperformance/src/models/bayesSteinShortSellCon.py
portfolioperformance/src/models/bayesianDataModel.py
portfolioperformance/src/models/ew.py
portfolioperformance/src/models/kanZhou.py
portfolioperformance/src/models/kanZhouEw.py
portfolioperformance/src/models/macKinlayPastor.py
portfolioperformance/src/models/meanVar.py
portfolioperformance/src/models/meanVarShortSellCon.py
portfolioperformance/src/models/minVar.py
portfolioperformance/src/models/minVarShortSellCon.py
portfolioperformance/src/utils/__init__.py
portfolioperformance/src/utils/filter.py
portfolioperformance/src/utils/quadprog.py
portfolioperformance/src/utils/sharedOptions.py
portfolioperformance/src/utils/statistics.py
portfolioperformance-1.1.0.dist-info/METADATA
portfolioperformance-1.1.0.dist-info/WHEEL
portfolioperformance-1.1.0.dist-info/top_level.txt
portfolioperformance-1.1.0.dist-info/RECORD
