Metadata-Version: 2.1
Name: portfolioperformance
Version: 1.1.0
Summary: Tool to test the out-of-sample performance of portfolio optimization models
Home-page: https://github.com/sidnand/portfolioperformance
Author: Siddharth Nand
Author-email: snand233@gmail.com
License: GNU
Classifier: Programming Language :: Python :: 3
Classifier: Operating System :: OS Independent
Requires-Python: <=3.12.0
Requires-Dist: numpy
Requires-Dist: pandas
Requires-Dist: scipy
Requires-Dist: qpsolvers >=4.3.1
Requires-Dist: quadprog >=0.1.12
